{
	"cardType": 83,
	"cardName": "Figurehead Knight",
	"effText": "When you draw, give each friendly character:\nDuring friendly turns: +1 W.\nDuring enemy turns: +1 E.",
	"effects": [
		{
			"triggerData": {
				"triggerCondition": "Draw",
				"triggerRestriction": {
					"$type": "Restrict.Triggering:AllOf:",
					"elements": [
						{ "$type": "Core.GamestateRestriction:ThisCardInPlay:" },
						{ "$type": "Core.GamestateRestriction:FriendlyTurn:" },
						{
							"$type": "Restrict.Triggering:PlayersMatch:",
							"firstPlayer": { "$type": "Players:TriggeringPlayer:" },
							"secondPlayer": { "$type": "Players:FriendlyPlayer:" }
						}
					]
				}
			},
			"subeffects": [
				{
					"$type": "Subeffect:ChangeAllCardStats:",
					
						"cardRestriction": {
							"$type": "Core.CardRestriction:AllOf:",
							"elements": [
							{ "$type": "Core.CardRestriction:Character:" },
							{ "$type": "Core.CardRestriction:Friendly:" }
						]
					},
					"wModifier": 1
				}
			]
		},
		{
			"triggerData": {
				"triggerCondition": "Draw",
				"triggerRestriction": {
					"$type": "Restrict.Triggering:AllOf:",
					"elements": [
						{ "$type": "Core.GamestateRestriction:ThisCardInPlay:" },
						{ "$type": "Restrict.Triggering:EnemyTurn:" },
						{
							"$type": "Restrict.Triggering:PlayersMatch:",
							"firstPlayer": { "$type": "Players:TriggeringPlayer:" },
							"secondPlayer": { "$type": "Players:FriendlyPlayer:" }
						}
					]
				}
			},
			"subeffects": [
				{
					"$type": "Subeffect:ChangeAllCardStats:",
					
						"cardRestriction": {
							"$type": "Core.CardRestriction:AllOf:",
							"elements": [
							{ "$type": "Core.CardRestriction:Character:" },
							{ "$type": "Core.CardRestriction:Friendly:" }
						]
					},
					"eModifier": 1
				}
			]
		}
	],
	"c": 4,
	"spellTypes": [
		"Enchant"
	],
	"subtypes": [
		"Tarocco",
		"Enchant"
	],
	"subtypeText": "Tarocco Enchant"
}