{
	"cardType": 67,
	"cardName": "PH453R",
	"effText": "Nimble Evasive Golem.",
	"effects": [],
	"attackingDefenderRestriction": {
		"$type": "Restrict.Cards:AttackingDefender:",
		"elements": [ {
			"$type": "Restrict.Triggering:CardFitsRestriction:",
			"card": { "$type": "Cards:ThisCardNow:" },
			"cardRestriction": { "$type": "Restrict.Cards:Active:" }
		} ]
	},
	"movementRestriction": {
		"$type": "Restrict.Spaces:MovementRestriction:",
		"moveThroughCards": true,
		"normalOnly": [ {
			"$type": "Restrict.Triggering:CardFitsRestriction:",
			"card": { "$type": "Cards:ThisCardNow:" },
			"cardRestriction": { "$type": "Restrict.Cards:Active:" }
		} ]
	},
	"keywords": [
		"Evasive"
	],
	"n": 3,
	"e": 3,
	"s": 10,
	"w": 3,
	"subtypes": [
		"Mech",
		"Golem"
	],
	"subtypeText": "Mech Golem"
}