{
	"cardType": 67,
	"cardName": "Modular Experimenter",
	"effText": "Once each turn, you can swap a Module attached to a friendly character for 2 distinct Modules in your hand.",
	"effects": [
		{
			"activationRestriction": {
				"$type": "Core.PlayerRestriction:ActivationRestriction:",
				"elements": [ { "$type": "Core.GamestateRestriction:MaxPerTurn:" } ]
			},
			"subeffects": [
				{
					"$type":"Subeffect:CardTarget:",
					"toSearch": { "$type": "ManyCards:Board:" },
					"cardRestriction":
					{
						"blurb": "character whose Module to swap out",
						"$type": "Restrict.Cards:AllOf:",
						"elements": [
							{ "$type": "Restrict.Cards:Character:" },
							{ "$type": "Restrict.Cards:Friendly:" },
							{
								"$type": "Restrict.Cards:HasAugment:",
								
						"cardRestriction": {
							"$type": "Restrict.Cards:AllOf:",
							"elements": [
										{
											"$type": "Restrict.Cards:Subtypes:",
											"subtypes": [ "Module" ]
										}
									]
								}
							}
						]
					}
				},
				{
					"$type": "Subeffect:CardTarget:",
					"cardRestriction": {
						"blurb": "Module to swap out",
						"elements": [
							{
								"$type": "Restrict.Cards:Subtypes:",
								"subtypes": [ "Module" ]
							},
							{
								"$type": "Restrict.Cards:Augments:",
								"singleCard": { "$type": "Cards:TargetIndex:" }
							}
						]
					}
				},
				{
					"$type": "Subeffect:CardTarget:",
					"toSearch": { "$type": "ManyCards:Hand:" },
					"cardRestriction":
					{
						"elements": [
							{ "$type": "Restrict.Cards:Augment:" },
							{
								"$type": "Restrict.Cards:Subtypes:",
								"subtypes": [ "Module" ]
							}
						]
					},
					"listRestriction": {
						"$type": "Core.ListRestriction:AllOf:",
						"elements": [
							{
								"$type": "Core.ListRestriction:Minimum:",
								"bound": { "$type": "Numbers:Constant:", "constant": 2 }
							},
							{
								"$type": "Core.ListRestriction:Maximum:",
								"bound": { "$type": "Numbers:Constant:", "constant": 2 }
							}
						]
					}
				},
				{
					"$type": "Subeffect:Hand:",
					"targetIndex": -3
				},
				{
					"$type": "Subeffect:Attach:",
					"targetIndex": -1,
					"targetToAttachTo": -4
				},
				{
					"$type": "Subeffect:Attach:",
					"targetIndex": -2,
					"targetToAttachTo": -4
				}
			]
		}
	],
	"n": 3,
	"e": 4,
	"s": 4,
	"w": 3,
	"subtypeText": "Craftsman"
}