{
	"cardType": 67,
	"cardName": "Armillaria Bulbosa",
	"effText": "Spores.\nWhen a Fungus pulses an enemy, deck-> or discard->summon Mycelium.",
	"effects": [
		{
			"blurb": "Army",
			"triggerData": {
				"triggerCondition": "Activate",
				"triggerRestriction": {
					"$type": "Restrict.Triggering:AllOf:",
					"elements": [
						{ "$type": "Restrict.Gamestate:ThisCardInPlay:" },
						{
							"$type": "Restrict.Triggering:CardFitsRestriction:",
							"card": { "$type": "Cards:CauseBefore:" },
							"cardRestriction": {
								"$type": "Restrict.Cards:Subtypes:",
								"subtypes": [ "Fungus" ]
							}
						},
						{
							"$type": "Restrict.Triggering:CardFitsRestriction:",
							"card": { "$type": "Cards:CardBefore:" },
							"cardRestriction": { "$type": "Restrict.Cards:Enemy:" }
						}
					]
				}
			},
			"subeffects": [
				{
					"$type": "Subeffect:CardTarget:",
					"blurb": "Mycelium to summon",
					
						"cardRestriction": {
							"$type": "Restrict.Cards:AllOf:",
							"elements": [
							{ "$type": "Restrict.Cards:Friendly:" },
							{
								"$type": "Restrict.Cards:Location:",
								"locations": [ "Deck", "Discard" ]
							},
							{
								"$type": "Restrict.Cards:Subtypes:",
								"subtypes": [ "Mycelium" ]
							},
							{ "$type": "Restrict.Cards:CanPlay:" }
						]
					},
					"targetIndex": -2
				},
				{
					"$type": "Subeffect:SpaceTarget:",
					"blurb": "Where to summon the Mycelium",
					"spaceRestriction": {
						"$type": "Restrict.Spaces:AllOf:",
						"elements": [
							{ "$type": "Restrict.Spaces:Empty:" },
							{
								"$type": "Restrict.Spaces:CanPlayCard:",
								"toPlay": { "$type": "Cards:TargetIndex:" }
							}
						]
					}
				},
				{
					"$type": "Subeffect:Play:"
				}
			]
		}
	],
	"keywords": [
		"Spores"
	],
	"n": 2,
	"e": 2,
	"s": 3,
	"w": 2,
	"subtypes": [
		"Digestive",
		"Fungus"
	],
	"subtypeText": "Digestive Fungus"
}