{
	"cardType": 83,
	"cardName": "Kaunan",
	"effText": "Runic.\nGive an adjacent character -3 EW.",
	"effects": [
		{
			"triggerData": {
				"triggerCondition": "Play",
				"triggerRestriction": {
					"$type": "Core.TriggerRestriction:CardsMatch:",
					"card": { "$type": "Cards:CardBefore:" },
					"other": { "$type": "Cards:ThisCardNow:" }
				}
			},
			"subeffects": [
				{
					"$type": "Subeffect:CardTarget:",
					"blurb": "for Kaunan to give -3 EW",
					"toSearch": { "$type": "ManyCards:Board:" },
					"cardRestriction": {
						"$type": "Core.CardRestriction:AllOf:",
						"elements": [
							{ "$type": "Core.CardRestriction:Character:" },
							{
								"$type": "Core.SpaceRestriction:AdjacentTo:",
								"space": { "$type": "Cards:ThisCardNow:" }
							}
						]
					}
				},
				{
					"$type": "Subeffect:ChangeCardStats:",
					"eModifier": -3,
					"wModifier": -3
				}
			]
		}
	],
	"PlayRestriction": {
		"$type": "Core.PlayRestriction:PlayRestriction:",
		"normalOnly": [ { "$type": "Core.GamestateRestriction:NeverValid:" } ],
		"recommendations": [ {
			"$type": "Core.SpaceRestriction:AdjacentTo:",
			"cardRestriction": { "$type": "Core.CardRestriction:Character:" }
		} ]
	},
	"c": 2,
	"spellTypes": [
		"Simple"
	],
	"subtypes": [
		"Rune",
		"Simple"
	],
	"subtypeText": "Rune Simple"
}