{
	"cardType": 83,
	"cardName": "None Defy the Lines",
	"effText": "Push each character to their closest edge. (Your choice if tied. You choose the order.)",
	"effects": [
		{
			"blurb": "Simple Effect",
			"triggerData": {
				"triggerCondition": "Play",
				"triggerRestriction": {
					"$type": "Restrict.Gamestate:CardsMatch:",
					"card": { "$type": "Identify.Cards:CardBefore:" },
					"other": { "$type": "Identify.Cards:ThisCardNow:" }
				}
			},
			"subeffects": [
				{
					"$type": "Subeffect:SkipToEffectOnImpossible:",
					"jumpIndices": [
						10
					]
				},
				{
					"$type": "Subeffect:CardTarget:",
					"blurb": "who to next be brought low by the Lines",
					"toSearch": { "$type": "Identify.ManyCards:Board:" },
					"cardRestriction": {
						"$type": "Restrict.Cards:AllOf:",
						"elements": [
							{ "$type": "Restrict.Cards:Character:" },
							{
								"$type": "Restrict.Cards:Not:",
								"negated": { "$type": "Restrict.Cards:Target:" }
							}
						]
					}
				},
				{
					"$type": "Subeffect:SkipToEffectOnImpossible:",
					"jumpIndices": [
						5
					]
				},
				{
					"$type": "Subeffect:SpaceTarget:",
					"blurb": "where on the Lines to bring them",
					"spaceRestriction": {
						"$type": "Restrict.Spaces:AllOf:",
						"elements": [
							{ "$type": "Restrict.Spaces:Empty:" },
							{ "$type": "Restrict.Spaces:Edge:" },
							{
								"$type": "Restrict.Spaces:CanMoveCard:",
								"toMove": { "$type": "Identify.Cards:TargetIndex:" }
							},
							{
								"$type": "Restrict.Spaces:SameDiagonal:",
								"other": { "$type": "Identify.Cards:TargetIndex:" }
							}
						]
					}
				},
				{
					"$type": "Subeffect:Move:"
				},
				{
					"$type": "Subeffect:Loop:",
					"jumpIndices": [
						0
					]
				}
			]
		}
	],
	"c": 4,
	"spellTypes": [
		"Simple"
	],
	"subtypes": [
		"Simple"
	],
	"subtypeText": "Simple"
}