{
	"cardType": 83,
	"cardName": "Yank",
	"effText": "Move a spell to a space adjacent to me. Draw 1 card.",
	"effects": [
		{
			"blurb": "The weight of binds",
			"triggerData": {
				"triggerCondition": "Play",
				"triggerRestriction": {
					"$type": "Core.TriggerRestriction:CardsMatch:",
					"card": { "$type": "Cards:CardBefore:" },
					"other": { "$type": "Cards:ThisCardNow:" }
				}
			},
			"subeffects": [
				{
					"$type": "Subeffect:CardTarget:",
					"blurb": "Spell to yank",
					"toSearch": { "$type": "ManyCards:Board:" },
					"cardRestriction": {
						"$type": "Core.CardRestriction:AllOf:",
						"elements": [
							{ "$type": "Core.CardRestriction:Spell:" },
							{
								"$type": "Core.CardRestriction:CanMove:",
								"spaceRestrictionSubeffectIndex": 1
							}
						]
					}
				},
				{
					"$type": "Subeffect:SpaceTarget:",
					"blurb": "Space to yank it to",
					"spaceRestriction": {
						"$type": "Core.SpaceRestriction:AllOf:",
						"elements": [
							{
								"$type": "Core.SpaceRestriction:CanMoveCard:",
								"toMove": { "$type": "Cards:TargetIndex:" }
							},
							{
								"$type": "Core.SpaceRestriction:AdjacentTo:",
								"space": { "$type": "Cards:ThisCardNow:" }
							}
						]
					}
				},
				{
					"$type": "Subeffect:Move:"
				},
				{
					"$type": "Subeffect:Draw:"
				}
			]
		}
	],
	"c": 2,
	"spellTypes": [
		"Simple"
	],
	"subtypeText": ""
}