{
	"cardType": 67,
	"cardName": "Arbiterary",
	"effText": "When you attach an Augment, give it +1 A. If you attached it to an enemy Avatar, it has A X, and I'm in a corner; give the Avatar -X E, attach it to me, and reset its A.",
	"effects": [
		{
			"triggerData": {
				"blurb": "Score Pass",
				"triggerCondition": "Augment Attached",
				"triggerRestriction": {
					"$type": "Restrict.Triggering:AllOf:",
					"elements": [
						{ "$type": "Restrict.Gamestate:ThisCardInPlay:" },
						{
							"$type": "Restrict.Gamestate:PlayersMatch:",
							"firstPlayer": { "$type": "Identify.Players:TriggeringPlayer:" },
							"secondPlayer": { "$type": "Identify.Players:FriendlyPlayer:" }
						}
					]
				}
			},
			"subeffects": [
				{
					"$type": "Subeffect:TargetTriggeringCard:"
				},
				{
					"$type": "Subeffect:SetXByNumberIdentity:",
					"numberIdentity": { 
						"$type": "Identify.Numbers:FromCardValue:",
						"card": { "$type": "Identify.Cards:TargetIndex:" },
						"cardValue": { "value": "A" }
					}
				},
				{
					"$type": "Subeffect:ChangeCardStats:",
					"aModifier": 1
				},
				{
					"$type": "Subeffect:TargetThis:"
				},
				{
					"$type": "Subeffect:ConditionalEnd:",
					"endIfTrue": {
						"$type": "Restrict.Gamestate:Not:",
						"negated": {
							"$type": "Restrict.Gamestate:CardFitsRestriction:",
							"card": { "$type": "Identify.Cards:TargetIndex:" },
							"cardRestriction": { "$type": "Restrict.Spaces:Corner:" }
						}
					}
				},
				{
					"$type": "Subeffect:TargetTargetsAugmentedCard:",
					"targetIndex": -2
				},
				{
					"$type": "Subeffect:ConditionalEnd:",
					"endIfTrue": {
						"$type": "Restrict.Gamestate:Not:",
						"negated": {
							"$type": "Restrict.Gamestate:CardFitsRestriction:",
							"card": { "$type": "Identify.Cards:TargetIndex:" },
							"cardRestriction": {
								"$type": "Restrict.Cards:AllOf:",
								"elements": [
									{ "$type": "Restrict.Cards:Enemy:" },
									{ "$type": "Restrict.Cards:Avatar:" }
								]
							}
						}
					}
				},
				{
					"$type": "Subeffect:ChangeCardStats:",
					"eMultiplier": -1
				},
				{
					"$type": "Subeffect:Attach:",
					"targetIndex": -3,
					"targetToAttachTo": -2
				},
				{
					"$type": "Subeffect:ResetStats:",
					"targetIndex": -3,
					"resetA": true
				}
			]
		}
	],
	"n": 1,
	"e": 7,
	"s": 11,
	"w": 3,
	"subtypeText": "Teammate"
}