{
	"cardType": 67,
	"cardName": "Inside Goalie Defender",
	"effText": "When you augment your adjacent Avatar, attach their Augment(s) to another character adjacent to me.",
	"effects": [
		{
			"triggerData": {
				"blurb": "Goal Kick",
				"triggerCondition": "Augmented",
				"triggerRestriction": {
					"$type": "Restrict.Triggering:AllOf:",
					"elements": [
						{ "$type": "Restrict.Gamestate:ThisCardInPlay:" },
						{
							"$type": "Restrict.Triggering:PlayersMatch:",
							"firstPlayer": { "$type": "Identify.Players:TriggeringPlayer:" },
							"secondPlayer": { "$type": "Identify.Players:FriendlyPlayer:" }
						},
						{
							"$type": "Restrict.Triggering:CardFitsRestriction:",
							"card": { "$type": "Identify.Cards:CardBefore:" },
							
						"cardRestriction": {
							"$type": "Restrict.Cards:AllOf:",
							"elements": [
									{ "$type": "Restrict.Cards:Friendly:" },
									{
										"$type": "Restrict.Cards:Location:",
										"locations": [ "Board" ]
									},
									{ "$type": "Restrict.Cards:Avatar:" },
									{
										"$type": "Restrict.Spaces:AdjacentTo:",
										"space": { "$type": "Identify.Cards:ThisCardNow:" }
									}
								]
							}
						}
					]
				}
			},
			"subeffects": [
				{
					"$type": "Subeffect:TargetTriggeringCard:"
				},
				{
					"$type": "Subeffect:CardTarget:",
					"blurb": "character to goal-kick Augment to",
					"toSearch": { "$type": "Identify.ManyCards:Board:" },
					"cardRestriction": {
						"$type": "Restrict.Cards:AllOf:",
						"elements": [
							{ "$type": "Restrict.Cards:Character:" },
							{
								"$type": "Restrict.Spaces:AdjacentTo:",
								"space": { "$type": "Identify.Cards:ThisCardNow:" }
							},
							{
								"$type": "Restrict.Cards:Not:",
								"negated": {
									"$type": "Restrict.Cards:CardsMatch:",
									"card": { "$type": "Identify.Cards:TargetIndex:" }
								}
							}
						]
					}
				},
				{
					"$type": "Subeffect:TargetAugments:",
					"targetIndex": -2
				},
				{
					"$type": "Subeffect:ConditionalEnd:",
					"endIfTrue": {
						"$type": "Restrict.Triggering:NumberFitsRestriction:",
						"number": { "$type": "Identify.Numbers:TargetCount:" },
						"restriction": {
							"$type": "Restrict.Numbers:Compare:",
							"comparison": { "$type": "Relationships.Number:LessThanEqual:" },
							"other": { "$type": "Identify.Numbers:Constant:", "constant": 2 }
						}
					}
				},
				{
					"$type": "Subeffect:Attach:",
					"targetToAttachTo": 1
				},
				{
					"$type": "Subeffect:LoopWhileHaveTargets:",
					"delete": true,
					"remainingTargets": 2,
					"jumpIndices": [
						4
					]
				}
			]
		}
	],
	"n": 1,
	"e": 5,
	"s": 1,
	"w": 0,
	"subtypeText": "Teammate"
}