{
	"cardType": 83,
	"cardName": "Soulselfdestruct",
	"effText": "Kill an adjacent friendly S X Ethereal. Deck->discard X Revenants.",
	"effects": [
		{
			"triggerData": {
				"triggerCondition": "Play",
				"triggerRestriction": {
					"$type": "Core.TriggerRestriction:CardsMatch:",
					"card": { "$type": "Cards:CardBefore:" },
					"other": { "$type": "Cards:ThisCardNow:" }
				}
			},
			"subeffects": [
				{
					"$type": "Subeffect:CardTarget:",
					"blurb": "Ethereal for Soulselfdestruct to kill",
					"toSearch": { "$type": "ManyCards:Board:" },
					"cardRestriction": {
						"$type": "Core.CardRestriction:AllOf:",
						"elements": [
							{ "$type": "Core.CardRestriction:Friendly:" },
							{
								"$type": "Core.CardRestriction:Subtypes:",
								"subtypes": [ "Ethereal" ]
							},
							{
								"$type": "Core.SpaceRestriction:AdjacentTo:",
								"space": { "$type": "Cards:ThisCardNow:" }
							}
						]
					}
				},
				{
					"$type": "Subeffect:SetXByNumberIdentity:",
					"numberIdentity": { 
						"$type": "Numbers:FromCardValue:",
						"card": { "$type": "Cards:TargetIndex:" },
						"cardValue": { "value": "S" }
					}
				},
				{
					"$type": "Subeffect:Discard:"
				},
				{
					"$type": "Subeffect:CardTarget:",
					"blurb": "card for Salvage Soul to discard",
					"toSearch": { "$type": "ManyCards:Deck:" },
					"cardRestriction": {
						"$type": "Core.CardRestriction:Subtypes:",
						"subtypes": [ "Revenant" ]
					}
				},
				{
					"$type": "Subeffect:Discard:"
				},
				{
					"$type": "Subeffect:XTimes:",
					"jumpIndices": [
						3
					]
				}
			]
		}
	],
	"PlayRestriction": {
		"$type": "Core.PlayRestriction:PlayRestriction:",
		"recommendations": [ {
			"$type": "Core.SpaceRestriction:AdjacentTo:",
			"cardRestriction": {
				"$type": "Core.CardRestriction:Subtypes:",
				"subtypes": [ "Ethereal" ]
			}
		} ]
	},
	"c": 1,
	"spellTypes": [
		"Simple"
	],
	"subtypes": [
		"Simple"
	],
	"subtypeText": "Simple"
}