{
	"cardType": 67,
	"cardName": "Cyan Linewalker",
	"effText": "Linewalk.\nWhen I move X spaces, move a distinct card X spaces.",
	"effects": [
		{
			"blurb": "Cyan Linewalked",
			"triggerData": {
				"triggerCondition": "Move",
				"triggerRestriction": {
					"$type": "Core.TriggerRestriction:CardsMatch:",
					"card": { "$type": "Cards:CardBefore:" },
					"other": { "$type": "Cards:ThisCardNow:" }
				}
			},
			"subeffects": [
				{
					"$type": "Subeffect:CardTarget:",
					"blurb": "for Cyan to move",
					"toSearch": { "$type": "ManyCards:Board:" },
					"cardRestriction": {
						"$type": "Core.CardRestriction:AllOf:",
						"elements": [
							{ "$type": "Core.CardRestriction:DistinctName:" },
							{
								"$type": "Core.CardRestriction:CanMove:",
								"spaceRestrictionSubeffectIndex": 1
							}
						]
					}
				},
				{
					"$type": "Subeffect:SpaceTarget:",
					"blurb": "where Cyan to move its target",
					"spaceRestriction": {
						"$type": "Core.SpaceRestriction:AllOf:",
						"elements": [
							{
								"$type": "Core.SpaceRestriction:CanMoveCard:",
								"toMove": { "$type": "Cards:TargetIndex:" }
							},
							{
								"$type": "Core.SpaceRestriction:CompareDistance:",
								"distanceTo": { "$type": "Cards:TargetIndex:" },
								"number": { "$type": "Numbers:Constant:", "constant": 1 }
							}
						]
					}
				},
				{
					"$type": "Subeffect:Move:"
				}
			]
		}
	],
	"keywords": [
		"Linewalk"
	],
	"n": 1,
	"e": 3,
	"s": 6,
	"w": 3,
	"subtypeText": "Linewalker Mage"
}